{
  "environment": "unknown",
  "domain_v1_progress": {
    "auth": {
      "target_route_count": 14,
      "migrated_v1_route_count": 6,
      "remaining_route_count": 8,
      "v1_migration_percent": 42.86
    },
    "admin": {
      "target_route_count": 332,
      "migrated_v1_route_count": 2,
      "remaining_route_count": 330,
      "v1_migration_percent": 0.6
    },
    "public": {
      "target_route_count": 27,
      "migrated_v1_route_count": 5,
      "remaining_route_count": 22,
      "v1_migration_percent": 18.52
    },
    "system": {
      "target_route_count": 27,
      "migrated_v1_route_count": 10,
      "remaining_route_count": 17,
      "v1_migration_percent": 37.04
    },
    "mobile": {
      "target_route_count": 6,
      "migrated_v1_route_count": 0,
      "remaining_route_count": 6,
      "v1_migration_percent": 0.0
    },
    "tenant": {
      "target_route_count": 103,
      "migrated_v1_route_count": 0,
      "remaining_route_count": 103,
      "v1_migration_percent": 0.0
    },
    "finance": {
      "target_route_count": 73,
      "migrated_v1_route_count": 0,
      "remaining_route_count": 73,
      "v1_migration_percent": 0.0
    },
    "misc": {
      "target_route_count": 831,
      "migrated_v1_route_count": 0,
      "remaining_route_count": 831,
      "v1_migration_percent": 0.0
    }
  },
  "generated_at": "2026-03-27T06:56:20.498804+00:00",
  "inventory_hash": "16854be07d57e48b823b7ac0dbc4737cb6f5bdbbe43ee25318e08c4fe0ebc705",
  "inventory_path": "/app/backend/app/bootstrap/route_inventory.json",
  "legacy_routes_remaining": 1417,
  "legacy_count": 1417,
  "migration_velocity": {
    "routes_migrated_this_pr": 0,
    "routes_remaining": 1417,
    "estimated_prs_remaining": 24
  },
  "namespaces": {
    "auth": 20,
    "admin": 335,
    "public": 32,
    "system": 38,
    "mobile": 6,
    "tenant": 103,
    "finance": 73,
    "misc": 833
  },
  "route_count": 1440,
  "runtime_name": "api",
  "v1_count": 23,
  "compat_required_count": 1417
}
